{
    "check_internet_button" : "off",
	"main_style" : { "padding" : 2, "relief": "ridge", "font":"Calibri", "fontsize" :15, "fontstyle": "bold",  "background":"#ccc" },
	"buttons" : [
	 {

	 "args": [ "C:\\Users\\074772\\Documents\\bdp\\access\\mystuff.kdbx" ],
	 "bname": "Keepass MyDB",
	 "command": [ "start", "C:\\Users\\074772\\Documents\\bdp\\access\\KeePass-2.34\\KeePass.exe" ]
	 },

	 {

	 "args": [ "\\\\ba\\esefdata\\CTO-Incubation\\BDP\\access\\bdp.kdbx" ],
	 "bname": "Keepass BDP",
	 "command": [ "start","C:\\Users\\074772\\Documents\\bdp\\access\\KeePass-2.34\\KeePass.exe" ]
	 },

	 {

	 "args": [ "" ],
	 "bname": "Backup BDP",
	 "command": [ "start","C:\\Users\\074772\\Documents\\bdp\\bdp-copy.cmd" ]
	 },
	 {
	 "args": [ "http://google.com" ],
	 "bname": "Google",
	 "command": ["start", "chrome" ]
	 },
	 {

	 "args": [ "https://weather.com/weather/5day/l/21042:4:US" ],
	 "bname": "Weather",
	 "command": ["start", "chrome" ]
	 }
	]

}
